pyhpeuxi/__init__.py
pyhpeuxi/common.py
pyhpeuxi/openapi.py
pyhpeuxi/utils_uxi.py
pyhpeuxi-1.0.2.dist-info/METADATA
pyhpeuxi-1.0.2.dist-info/WHEEL
pyhpeuxi-1.0.2.dist-info/licenses/LICENSE.md
pyhpeuxi-1.0.2.dist-info/RECORD
